{
  "user": [
    {
      "name": "Jennifer Hernandez",
      "id": 1
    },
    {
      "name": "Betty Hall",
      "id": 2
    },
    {
      "name": "George Johnson",
      "id": 3
    },
    {
      "name": "Brenda Brown",
      "id": 4
    },
    {
      "name": "Scott Thompson",
      "id": 5
    },
    {
      "name": "罗强",
      "id": 6
    },
    {
      "name": "叶平",
      "id": 7
    },
    {
      "name": "邓霞",
      "id": 8
    },
    {
      "name": "谢秀兰",
      "id": 9
    },
    {
      "name": "曾娜",
      "id": 10
    },
    {
      "name": "林平",
      "id": 11
    },
    {
      "name": "林平",
      "id": 12
    },
    {
      "name": "林平",
      "id": 13
    },
    {
      "name2": "廖勇",
      "str": "ssss",
      "id": 14
    },
    {
      "name": "Linda Brown",
      "str": "经热强之些。装放。称况。又政。",
      "id": 15
    }
  ]
}